smart_commit_msg/__init__.py
smart_commit_msg-0.1.1.dist-info/METADATA
smart_commit_msg-0.1.1.dist-info/WHEEL
smart_commit_msg-0.1.1.dist-info/entry_points.txt
smart_commit_msg-0.1.1.dist-info/RECORD
