Metadata-Version: 2.3
Name: smart-commit-msg
Version: 0.1.1
Summary: Builds a smart commit message using LLMs
Author-email: ariG23498 <aritra.born2fly@gmail.com>
Requires-Python: >=3.9
Requires-Dist: fire>=0.7.0
Requires-Dist: huggingface-hub>=0.26.1
Requires-Dist: ruff>=0.7.1
